{
	"id": "b633c534-ed2b-449e-88b9-69d8cbf74498",
	"name": "https://localhost:8443 WebService",
	"values": [
		{
			"key": "protocol",
			"value": "https",
			"enabled": true
		},
		{
			"key": "host",
			"value": "localhost",
			"enabled": true
		},
		{
			"key": "port",
			"value": "8443",
			"enabled": true
		},
		{
			"key": "userName",
			"value": "WebService",
			"enabled": true
		},
		{
			"key": "password",
			"value": "WebService",
			"enabled": true
		},
		{
			"key": "clientId",
			"value": "11",
			"enabled": true
		},
		{
			"key": "roleId",
			"value": "50004",
			"enabled": true
		},
		{
			"key": "organizationId",
			"value": "11",
			"enabled": true
		},
		{
			"key": "warehouseId",
			"value": "103",
			"enabled": true
		},
		{
			"key": "language",
			"value": "en_US",
			"enabled": true
		}
	],
	"_postman_variable_scope": "environment",
	"_postman_exported_at": "2021-09-14T11:48:44.727Z",
	"_postman_exported_using": "Postman/8.12.1"
}